[
    {
        "device_id": "device123",
        "key": "key12345",
        "expirydate": "31-12-2025",
        "Allowoffline": true
    },
    {
        "device_id": "device456",
        "key": "key67890",
        "expirydate": "15-06-2025",
        "Allowoffline": false
    },
    {
        "device_id": "ce115e0590bb1f3c",
        "key": "test",
        "expirydate": "11-09-2035",
        "Allowoffline": true
    },
    {
        "device_id": "9c6990cbce17ab3e",
        "key": "stock",
        "expirydate": "15-06-2066",
        "Allowoffline": true
    },
    {
        "device_id": "f8a50ea95eeb4254",
        "key": "stock2",
        "expirydate": "15-06-2066",
        "Allowoffline": true
    },
    {
        "device_id": "58a04fdb8e703378",
        "key": "stock1",
        "expirydate": "15-06-2044",
        "Allowoffline": true
    },
    {
        "device_id": "fe0cd9b9b7bdc97d",
        "key": "wincare2",
        "expirydate": "15-06-2027",
        "Allowoffline": false
    },
    {
        "device_id": "e961f410ad8789c3",
        "key": "ductrinh",
        "expirydate": "13-11-2029",
        "Allowoffline": false
    },
    {
        "device_id": "87bc7ff2a451fee0",
        "key": "ductrinh1",
        "expirydate": "14-11-2035",
        "Allowoffline": false
    },
    {
        "device_id": "04bcb3b6c33cdc41",
        "key": "wincareanpham",
        "expirydate": "13-11-2025",
        "Allowoffline": false
    },
    {
        "device_id": "7a43d1589a569397",
        "key": "mcsthanhphong22",
        "expirydate": "15-06-2028",
        "Allowoffline": false
    },
    {
        "device_id": "f0ada2e99510cc5a",
        "key": "pgmshoanghai",
        "expirydate": "11-11-2025",
        "Allowoffline": false
    },
    {
        "device_id": "1ba1c745d3a87cf5",
        "key": "mcssonlam",
        "expirydate": "15-06-2027",
        "Allowoffline": false
    },
    {
        "device_id": "777b1df57c3ec838",
        "key": "mcsmrthoai",
        "expirydate": "06-11-2029",
        "Allowoffline": false
    },
    {
        "device_id": "50aacba485eb29f5",
        "key": "mcsvutruong",
        "expirydate": "08-12-2025",
        "Allowoffline": false
    },
    {
        "device_id": "fd18384bbf7b3262",
        "key": "dailemobiw",
        "expirydate": "05-11-2028",
        "Allowoffline": false
    },
    {
        "device_id": "c0d423cad4181fe6",
        "key": "dailedmsone",
        "expirydate": "07-11-2029",
        "Allowoffline": false
    },
    {
        "device_id": "6f8a394173ee7afa",
        "key": "dailemark1",
        "expirydate": "07-11-2025",
        "Allowoffline": false
    },
    {
        "device_id": "48bd27f26c371c5f",
        "key": "mcstuandinh",
        "expirydate": "15-06-2045",
        "Allowoffline": false
    },
    {
        "device_id": "7ca4ba2c23f3eb08",
        "key": "mcsphiden",
        "expirydate": "19-06-2035",
        "Allowoffline": false
    },
    {
        "device_id": "f798fa10013be776",
        "key": "mcstrongthin",
        "expirydate": "15-06-2045",
        "Allowoffline": true
    },
    {
        "device_id": "56b27e76068ce3bc",
        "key": "mcstuanthanh",
        "expirydate": "15-06-2027",
        "Allowoffline": false
    },
    {
        "device_id": "163ac34293f54263",
        "key": "mcsphankhoa",
        "expirydate": "15-06-2027",
        "Allowoffline": false
    },
    {
        "device_id": "7ade4e31d4d793ba",
        "key": "mcsvann",
        "expirydate": "22-10-2037",
        "Allowoffline": false
    },
    {
        "device_id": "da216cfc32921f66",
        "key": "mcsduykhanh",
        "expirydate": "15-12-2037",
        "Allowoffline": false
    },
    {
        "device_id": "5df314629c7a3c11",
        "key": "dmsone1",
        "expirydate": "15-12-2027",
        "Allowoffline": false
    },
    {
        "device_id": "fbf48cc07e1ac247",
        "key": "mcsthanphong",
        "expirydate": "15-12-2027",
        "Allowoffline": false
    },
    {
        "device_id": "3e993293609c73a1",
        "key": "jgsnguyenhien",
        "expirydate": "15-12-2027",
        "Allowoffline": false
    },
    {
        "device_id": "5496c6c25b142ee5",
        "key": "mcshoangphuong",
        "expirydate": "15-12-2027",
        "Allowoffline": false
    },
    {
        "device_id": "772dace3e615ff86",
        "key": "dailerichy2k",
        "expirydate": "07-11-2029",
        "Allowoffline": false
    },
    {
        "device_id": "3306af06b8ac089d",
        "key": "mcsbirainn",
        "expirydate": "15-06-2027",
        "Allowoffline": false
    },
    {
        "device_id": "65ddea1a94ee6230",
        "key": "lge11",
        "expirydate": "15-06-2027",
        "Allowoffline": false
    },
    {
        "device_id": "4f05b166b04dc82a",
        "key": "huyhoang",
        "expirydate": "16-06-2037",
        "Allowoffline": false
    },  
    {
        "device_id": "c37c57e263495f6a",
        "key": "lamhongmai",
        "expirydate": "15-06-2037",
        "Allowoffline": false
    },  
    {
        "device_id": "c18ce06158c90af0",
        "key": "lge22",
        "expirydate": "15-06-2037",
        "Allowoffline": false
    },  
    {
        "device_id": "a2e450e4e117e133",
        "key": "lgephuocbinh",
        "expirydate": "15-06-2037",
        "Allowoffline": false
    },  
    {
        "device_id": "fef706decf1a825d",
        "key": "xukaxinh",
        "expirydate": "15-06-2037",
        "Allowoffline": false
    },
    {
        "device_id": "b7543b46d7d1aed3",
        "key": "kimngoc",
        "expirydate": "15-09-2037",
        "Allowoffline": false
    },
    {
        "device_id": "0009a8c42f00755f",
        "key": "nguyenxn",
        "expirydate": "15-06-2036",
        "Allowoffline": false
    },
    {
        "device_id": "92de2990106b8f36",
        "key": "nguyenxn1",
        "expirydate": "15-06-2036",
        "Allowoffline": false
    },
    {
        "device_id": "11f8871b120afa44",
        "key": "ngocrichy",
        "expirydate": "15-06-2037",
        "Allowoffline": false
    },
    {
        "device_id": "ed6ba9a1c4ba313c",
        "key": "ngocrichy22",
        "expirydate": "15-10-2027",
        "Allowoffline": false
    },
    {
        "device_id": "4a38d0eb7326e03b",
        "key": "toanrichy",
        "expirydate": "15-06-2037",
        "Allowoffline": false
    },
    {
        "device_id": "4f29520d2e981662",
        "key": "lanhkarofi",
        "expirydate": "19-10-2035",
        "Allowoffline": true
    },
    {
        "device_id": "c71e6fdef66d51fc",
        "key": "richy2",
        "expirydate": "15-06-2037",
        "Allowoffline": false
    },
    {
        "device_id": "b0b4278d84b45542",
        "key": "richy3",
        "expirydate": "25-02-2030",
        "Allowoffline": false
    },
    {
        "device_id": "f5c82e3074bb9405",
        "key": "richyngoc",
        "expirydate": "25-02-2030",
        "Allowoffline": false
    }, 
    {
        "device_id": "b11d11e155854546",
        "key": "richy333",
        "expirydate": "25-02-2030",
        "Allowoffline": false
    }, 
    {
        "device_id": "9883097edb43da35",
        "key": "richy3",
        "expirydate": "25-02-2030",
        "Allowoffline": false
    }, 
    {
        "device_id": "ac619a5ea7e16a96",
        "key": "daileofficial",
        "expirydate": "19-06-2039",
        "Allowoffline": true
    },
    {
        "device_id": "f9ae4b7ad8946960",
        "key": "dailemi11",
        "expirydate": "19-06-2039",
        "Allowoffline": false
    },
    {
        "device_id": "87ee37157fd606a0",
        "key": "dailesaleone",
        "expirydate": "01-11-2035",
        "Allowoffline": false
    },
    {
        "device_id": "058e441d84de1d21",
        "key": "dailemcs44",
        "expirydate": "22-06-2034",
        "Allowoffline": false
    },
    {
        "device_id": "44c3ccac4a6940e5",
        "key": "dailemcs22",
        "expirydate": "19-09-2039",
        "Allowoffline": false
    },
    {
        "device_id": "435044d06d28aa98",
        "key": "dailemcs33",
        "expirydate": "19-06-2039",
        "Allowoffline": false
    },
    {
        "device_id": "c28f398a3e49b18d",
        "key": "dailevcam",
        "expirydate": "04-11-2029",
        "Allowoffline": false
    },
    {
        "device_id": "40146b0a0e3221e2",
        "key": "dailesfagps",
        "expirydate": "12-11-2025",
        "Allowoffline": true
    },
    {
        "device_id": "22d3c1b4a24f410e",
        "key": "dailerichy",
        "expirydate": "19-06-2039",
        "Allowoffline": true
    },
    {
        "device_id": "f8a4f51e82b89436",
        "key": "dmsprodaile",
        "expirydate": "19-06-2039",
        "Allowoffline": false
    },
    {
        "device_id": "c28f398a3e49b18d",
        "key": "dailegps",
        "expirydate": "19-06-2039",
        "Allowoffline": false
    },
    {
        "device_id": "3979d9de201c695c",
        "key": "tuanrichy",
        "expirydate": "19-06-2039",
        "Allowoffline": false
    },
    {
        "device_id": "8918f261b786fe1c",
        "key": "tuanrichy1",
        "expirydate": "19-06-2029",
        "Allowoffline": false
    },
    {
        "device_id": "ac8acada80a2f9c2",
        "key": "richy33",
        "expirydate": "15-06-2036",
        "Allowoffline": false
    },  
    {
        "device_id": "79294656d17a41c0",
        "key": "chihanh1",
        "expirydate": "25-02-2030",
        "Allowoffline": false
    },
    {
        "device_id": "42d0b05c1d935c69",
        "key": "kirin",
        "expirydate": "26-02-2030",
        "Allowoffline": false
    },
    {
        "device_id": "08c757613af4ce4a",
        "key": "dungdang11",
        "expirydate": "28-09-2035",
        "Allowoffline": false
    },
    {
        "device_id": "1c21a376ee02b7cd",
        "key": "dungdang",
        "expirydate": "28-09-2035",
        "Allowoffline": false
    },
    {
        "device_id": "f427e1c2327ae8bc",
        "key": "xuandat22",
        "expirydate": "05-10-2045",
        "Allowoffline": false
    },
    {
        "device_id": "f41e0be89e032045",
        "key": "xuandat44",
        "expirydate": "25-06-2037",
        "Allowoffline": false
    },
    {
        "device_id": "c482a04d37ea7793",
        "key": "xuandat",
        "expirydate": "25-06-2037",
        "Allowoffline": false
    },
    {
        "device_id": "7c92d5a981f08750",
        "key": "ngochaisony",
        "expirydate": "19-06-2030",
        "Allowoffline": false
    },
    {
        "device_id": "7eb1b4c7a218e81a",
        "key": "suhaotoshiba",
        "expirydate": "04-10-2045",
        "Allowoffline": false
    },
    {
        "device_id": "02ff2d23dc4c3924",
        "key": "hooritoshiba",
        "expirydate": "04-10-2045",
        "Allowoffline": true
    },
    {
        "device_id": "f2a92930673057c4",
        "key": "vantoshiba",
        "expirydate": "19-09-2040",
        "Allowoffline": true
    },
    {
        "device_id": "2d55555ad842554c",
        "key": "duchuytoshiba",
        "expirydate": "19-09-2040",
        "Allowoffline": false
    },
    {
        "device_id": "fb4e104ee87f2f18",
        "key": "haitoshiba",
        "expirydate": "19-09-2040",
        "Allowoffline": false
    },
    {
        "device_id": "85e601a36fee4012",
        "key": "quynhxinh",
        "expirydate": "16-09-2040",
        "Allowoffline": false
    },
    {
        "device_id": "87923fb5ff6a06fa",
        "key": "quynhxinh22",
        "expirydate": "16-09-2040",
        "Allowoffline": false
    },
    {
        "device_id": "1b8f66c8fc4a4db0",
        "key": "thuongaqua",
        "expirydate": "16-02-2040",
        "Allowoffline": false
    },
    {
        "device_id": "09f4c6c64e21a4d4",
        "key": "aqua",
        "expirydate": "26-02-2040",
        "Allowoffline": false
    },
    {
        "device_id": "796fc96e62df5af6",
        "key": "chihanh22",
        "expirydate": "18-09-2055",
        "Allowoffline": false
    },
    {
        "device_id": "b5612b59ea48d190",
        "key": "quynhrichy",
        "expirydate": "18-09-2065",
        "Allowoffline": false
    },
    {
        "device_id": "031e3faf317adc23",
        "key": "tingco22",
        "expirydate": "18-09-2045",
        "Allowoffline": false
    },
    {
        "device_id": "b5612b59ea48d190",
        "key": "quynhxinhrichy",
        "expirydate": "18-09-2029",
        "Allowoffline": false
    },
    {
        "device_id": "9810d7b1b1938874",
        "key": "tingco33",
        "expirydate": "18-09-2035",
        "Allowoffline": false
    },
    {
        "device_id": "fd447451118d2a47",
        "key": "sfanam11",
        "expirydate": "14-09-2045",
        "Allowoffline": false
    },
    {
        "device_id": "bec5496f0605eade",
        "key": "sfahapham",
        "expirydate": "14-11-2045",
        "Allowoffline": true
    },
    {
        "device_id": "ac63345f338aa928",
        "key": "sfakun",
        "expirydate": "14-09-2045",
        "Allowoffline": false
    },
    {
        "device_id": "f62665eb70a7fede",
        "key": "sfamay",
        "expirydate": "14-09-2045",
        "Allowoffline": false
    },
    {
        "device_id": "64e5cb2a1972b93c",
        "key": "sfameohoang",
        "expirydate": "14-09-2045",
        "Allowoffline": false
    },
    {
        "device_id": "dfc7aa84ea8ced21",
        "key": "sfaphamphuong",
        "expirydate": "14-09-2045",
        "Allowoffline": true
    },
    {
        "device_id": "4ed6e829cb466a20",
        "key": "sfaluyendo1",
        "expirydate": "14-09-2045",
        "Allowoffline": false
    },
    {
        "device_id": "ca20385ede563d88",
        "key": "sfabinhkun",
        "expirydate": "14-09-2045",
        "Allowoffline": false
    },
    {
        "device_id": "fdb6eeab16a36824",
        "key": "sfathanhmai33",
        "expirydate": "14-09-2045",
        "Allowoffline": false
    },
    {
        "device_id": "685e34f570f65fa0",
        "key": "sfathanhmai",
        "expirydate": "14-09-2045",
        "Allowoffline": false
    },
    {
        "device_id": "f8a50ea9d176ff99",
        "key": "sfathanhnguyen",
        "expirydate": "19-11-2025",
        "Allowoffline": true
    },
    {
        "device_id": "8cddbeab3769b825",
        "key": "sfathanhnguyen1",
        "expirydate": "14-10-2035",
        "Allowoffline": true
    },
    {
        "device_id": "a4c3fa1cb29e3a41",
        "key": "sfahanhngan",
        "expirydate": "16-10-2035",
        "Allowoffline": false
    },
    {
        "device_id": "faadbe32b24aafe8",
        "key": "sfathuyhuong",
        "expirydate": "17-09-2035",
        "Allowoffline": false
    },
    {
        "device_id": "574d972a309dbd51",
        "key": "sfahang1",
        "expirydate": "17-09-2035",
        "Allowoffline": false
    },
    {
        "device_id": "371d1d15960c42c6",
        "key": "sfanguyenquan1",
        "expirydate": "17-09-2035",
        "Allowoffline": false
    },
    {
        "device_id": "d27e5bbc88daf1e3",
        "key": "sfanguyenhoai1",
        "expirydate": "17-09-2045",
        "Allowoffline": false
    }, 
    {
        "device_id": "8d028233820c60d0",
        "key": "sfathuy1",
        "expirydate": "17-09-2065",
        "Allowoffline": false
    },
    {
        "device_id": "a4d4414d1db0803b",
        "key": "wincaredaile",
        "expirydate": "06-11-2026",
        "Allowoffline": false
    }, 
    {
        "device_id": "25425acd5db0fa24",
        "key": "richy44",
        "expirydate": "16-09-2044",
        "Allowoffline": false
    }, 
    {
        "device_id": "122a488affd70eeb",
        "key": "tansopoka",
        "expirydate": "05-10-2029",
        "Allowoffline": false
    },
    {
        "device_id": "f14c10708a5a7db7",
        "key": "daile11",
        "expirydate": "15-10-2030",
        "Allowoffline": false
    },
    {
        "device_id": "9e850a46e6e897de",
        "key": "thienlong",
        "expirydate": "13-10-2029",
        "Allowoffline": false
    },
    {
        "device_id": "8ecbf8f54c1c4304",
        "key": "nguyensopoka",
        "expirydate": "17-10-2035",
        "Allowoffline": false
    },
    {
        "device_id": "0b2994a6cff25302",
        "key": "pgmsphantho",
        "expirydate": "18-12-2030",
        "Allowoffline": false
    },
    {
        "device_id": "a8f1e05c461f1cc1",
        "key": "vifonetuongvi",
        "expirydate": "17-10-2035",
        "Allowoffline": false
    },
    {
        "device_id": "f6a6f083c86e3989",
        "key": "vivo1",
        "expirydate": "26-09-2029",
        "Allowoffline": false
    },
    {
        "device_id": "7d72dc2aecd0e7f8",
        "key": "vivo2",
        "expirydate": "26-09-2035",
        "Allowoffline": false
    }
]
